markdown_extract/__init__.py
markdown_extract/extractor.py
markdown_extract/parser.py
markdown_extract-0.1.1.dist-info/licenses/LICENSE
markdown_extract-0.1.1.dist-info/METADATA
markdown_extract-0.1.1.dist-info/WHEEL
markdown_extract-0.1.1.dist-info/top_level.txt
markdown_extract-0.1.1.dist-info/RECORD
