Metadata-Version: 2.4
Name: markdown_extract
Version: 0.1.1
Summary: A library to extract sections from Markdown files based on headers.
Author-email: Tongyuan Miao <david.tongyuan@gmail.com>
License: MIT License
Project-URL: Homepage, https://github.com/cogitoergo-sum/markdown_extract
Project-URL: Bug Tracker, https://github.com/cogitoergo-sum/markdown_extract/issues
Keywords: markdown,parser,extraction,headers
Classifier: Programming Language :: Python :: 3
Classifier: License :: OSI Approved :: MIT License
Classifier: Operating System :: OS Independent
Requires-Python: >=3.7
License-File: LICENSE
Dynamic: license-file
